postman2runner/__init__.py
postman2runner/cli.py
postman2runner/compat.py
postman2runner/core.py
postman2runner/parser.py
postman2runner/utils.py
tests/__init__.py
tests/test_postmanparser.py
postman2runner-0.0.2.dist-info/LICENSE
postman2runner-0.0.2.dist-info/METADATA
postman2runner-0.0.2.dist-info/WHEEL
postman2runner-0.0.2.dist-info/entry_points.txt
postman2runner-0.0.2.dist-info/top_level.txt
postman2runner-0.0.2.dist-info/RECORD
