Metadata-Version: 2.1
Name: postman2runner
Version: 0.0.2
Summary: Convert POSTMAN data to JSON testcases for HttpRunner.
Home-page: https://github.com/gerrywen/postman2runner
Author: gerrywen
Author-email: blog@gerrywen.com
License: MIT
Keywords: postman converter json
Platform: UNKNOWN
Classifier: Development Status :: 3 - Alpha
Classifier: Programming Language :: Python :: 2.7
Classifier: Programming Language :: Python :: 3.4
Classifier: Programming Language :: Python :: 3.5
Classifier: Programming Language :: Python :: 3.6
Classifier: Programming Language :: Python :: 3.7
